pytest_slackfixtures.py
slacktools_slackfixtures-1.0.0.dist-info/LICENSE
slacktools_slackfixtures-1.0.0.dist-info/METADATA
slacktools_slackfixtures-1.0.0.dist-info/WHEEL
slacktools_slackfixtures-1.0.0.dist-info/entry_points.txt
slacktools_slackfixtures-1.0.0.dist-info/top_level.txt
slacktools_slackfixtures-1.0.0.dist-info/RECORD
