Metadata-Version: 2.1
Name: slacktools-slackfixtures
Version: 1.0.0
Summary: UNKNOWN
Home-page: https://github.com/danpoland/slacktools-slackfixtures
Author: Daniel Poland
Author-email: dan@crispy.dev
License: UNKNOWN
Platform: UNKNOWN
Classifier: Programming Language :: Python :: 3
Classifier: License :: OSI Approved :: MIT License
Classifier: Operating System :: OS Independent
Classifier: Framework :: Pytest
Requires-Python: >=3.6
Requires-Dist: pytest (~=5.3.5)
Requires-Dist: pytest-mock (~=2.0.0)
Requires-Dist: slackclient (~=2.5.0)
